foostrap/__init__.py
foostrap/interface.py
foostrap/preproc.py
foostrap/stats_numba.py
foostrap/stats_py.py
foostrap-1.2.1.dist-info/METADATA
foostrap-1.2.1.dist-info/WHEEL
foostrap-1.2.1.dist-info/licenses/LICENSE
foostrap-1.2.1.dist-info/RECORD
