Metadata-Version: 2.4
Name: foostrap
Version: 1.2.1
Summary: Fast Bootstrap statistics using Numba
Project-URL: Repository, https://github.com/japlete/foostrap
Author-email: Jose A Poblete <jose.a.poblete@pm.me>
License: MIT License
License-File: LICENSE
Keywords: ab testing,bootstrap,confidence interval
Classifier: License :: OSI Approved :: MIT License
Classifier: Programming Language :: Python :: 3
Requires-Python: >=3.10
Requires-Dist: numba>=0.61
Requires-Dist: numpy>=1.25
Requires-Dist: scipy>=1.11
Provides-Extra: iccrt
Requires-Dist: icc-rt; extra == 'iccrt'
